MANIFEST.in
README.md
setup.cfg
setup.py
rdflib_zodb/ZODB.py
rdflib_zodb/__init__.py
rdflib_zodb.egg-info/PKG-INFO
rdflib_zodb.egg-info/SOURCES.txt
rdflib_zodb.egg-info/dependency_links.txt
rdflib_zodb.egg-info/entry_points.txt
rdflib_zodb.egg-info/requires.txt
rdflib_zodb.egg-info/top_level.txt
test/__init__.py
test/__init__.pyc
test/context_case.py
test/context_case.pyc
test/graph_case.py
test/graph_case.pyc
test/test_store_performance.py
test/test_store_performance.pyc
test/test_zodb.py
test/test_zodb.pyc
test/sp2b/10ktriples.n3
test/sp2b/1ktriples.n3
test/sp2b/25ktriples.n3
test/sp2b/2ktriples.n3
test/sp2b/3ktriples.n3
test/sp2b/500triples.n3
test/sp2b/50ktriples.n3
test/sp2b/5ktriples.n3