Metadata-Version: 1.1
Name: rdflib-zodb
Version: 1.0
Summary: rdflib extension adding ZODB as back-end store
Home-page: http://github.com/RDFLib/rdflib-zodb
Author: Graham Higgins
Author-email: gjhiggins@gmail.com
License: BSD
Platform: any
Classifier: Programming Language :: Python
Classifier: Programming Language :: Python :: 2
Classifier: Programming Language :: Python :: 2.6
Classifier: Programming Language :: Python :: 2.7
Classifier: Programming Language :: Python :: 3
Classifier: Programming Language :: Python :: 3.2
Classifier: Programming Language :: Python :: 3.3
Classifier: Programming Language :: Python :: Implementation :: PyPy
Classifier: License :: OSI Approved :: BSD License
Classifier: Topic :: Software Development :: Libraries :: Python Modules
Classifier: Operating System :: OS Independent
Classifier: Natural Language :: English
